fastset/__init__.py
fastset-0.0.1.dist-info/METADATA
fastset-0.0.1.dist-info/WHEEL
fastset-0.0.1.dist-info/RECORD
